{
  "current_version": {
    "version": "2018.03.01-2225",
    "name": "Navi"
  },
  "history": [
    {
      "version": "2018.03.01-2225",
      "type": "BUGFIX",
      "change": "fonts should be ordered alphabetically."
    },
    {
      "version": "2018.03.01-1842",
      "type": "BUGFIX",
      "change": "fix text replacer bug."
    },
    {
      "version": "2018.03.01-1608",
      "type": "MINOR_FEATURE",
      "change": "Font add/remove commands."
    },
    {
      "version": "2018.03.01-1457",
      "type": "BUGFIX",
      "change": "Text replacers more stable format."
    },
    {
      "version": "2018.02.28-2114",
      "type": "MAJOR_FEATURE",
      "change": "Fonts command."
    },
    {
      "version": "2018.02.28-2003",
      "type": "MINOR_FEATURE",
      "change": "Sending extension loading errors to the websocket."
    },
    {
      "version": "2018.02.28-1933",
      "type": "BUGFIX",
      "change": "Word cloud colour image now centered."
    },
    {
      "version": "2018.02.27-2305",
      "type": "BUGFIX",
      "change": "Help command shortens descriptions if too long."
    },
    {
      "version": "2018.02.27-2255",
      "type": "MINOR_FEATURE",
      "change": "Draw text now uses the flag system and thus provides more options."
    },
    {
      "version": "2018.02.27-1905",
      "type": "MINOR_FEATURE",
      "change": "Changed word cloud to use flag system and added features."
    },
    {
      "version": "2018.02.25-2313",
      "type": "MINOR_FEATURE",
      "change": "Version changes uses the new Flags system now."
    },
    {
      "version": "2018.02.25-2242",
      "type": "MAJOR_FEATURE",
      "change": "Added message commands like embed and quote."
    },
    {
      "version": "2018.02.25-2012",
      "type": "BUGFIX",
      "change": "Replacers don't trigger in commands"
    },
    {
      "version": "2018.02.25-1846",
      "type": "MAJOR_FEATURE",
      "change": "Created Draw commands."
    },
    {
      "version": "2018.02.24-1643",
      "type": "MINOR_FEATURE",
      "change": "Complex replacers now display test results."
    },
    {
      "version": "2018.02.24-1501",
      "type": "BUGFIX",
      "change": "Fixed deleting replacers."
    },
    {
      "version": "2018.02.24-1302",
      "type": "BUGFIX",
      "change": "Replacers might actually work now"
    },
    {
      "version": "2018.02.24-0021",
      "type": "BUGFIX",
      "change": "Showing new changes should work now"
    },
    {
      "version": "2018.02.24-0000",
      "type": "MAJOR_FEATURE",
      "change": "Replace now supports lots of cool stuff?"
    },
    {
      "version": "2018.02.23-1418",
      "type": "MINOR_FEATURE",
      "change": "Show command supports images"
    },
    {
      "version": "2018.02.23-1338",
      "type": "BUGFIX",
      "change": "Sending error message for Firefox marionette returning no data"
    },
    {
      "version": "2018.02.23-1234",
      "type": "BUGFIX",
      "change": "Changing presence to afk should maybe hopefully fix things?"
    },
    {
      "version": "2018.02.21-1933",
      "type": "MAJOR_FEATURE",
      "change": "ASCII is now Text and can do some cool custom replacer stuff."
    },
    {
      "version": "2018.02.20-1716",
      "type": "MINOR_FEATURE",
      "change": "Can show new changes."
    },
    {
      "version": "2018.02.20-1704",
      "type": "BUGFIX",
      "change": "Correctly formatting version stamps."
    },
    {
      "version": "2018.02.20-1650",
      "type": "BUGFIX",
      "change": "Implemented comparison operators for version stamps."
    },
    {
      "version": "2018.02.20-1642",
      "type": "MAJOR_FEATURE",
      "change": "Added version commands for Gisi"
    },
    {
      "version": "2018.02.20-1402",
      "type": "MAJOR_FEATURE",
      "change": "Added version system."
    }
  ]
}
